magnet_parser/__init__.py
magnet_parser/magnet.py
magnet_parser-0.1.1.dist-info/METADATA
magnet_parser-0.1.1.dist-info/WHEEL
magnet_parser-0.1.1.dist-info/entry_points.txt
magnet_parser-0.1.1.dist-info/top_level.txt
magnet_parser-0.1.1.dist-info/RECORD
