Metadata-Version: 2.1
Name: magnet-parser
Version: 0.1.1
Summary: A module for decoding and encoding magnet URIs.
Author: Muhammad Al Fajri
Author-email: Muhammad Al Fajri <admin@pyjri.com>
Keywords: magnet,parser,URI
Classifier: Programming Language :: Python :: 3
Classifier: License :: OSI Approved :: MIT License
Classifier: Operating System :: OS Independent
